mathlab_pg/__init__.py
mathlab_pg/futures_api.py
mathlab_pg_api/__init__.py
mathlab_pg_api/futures_api.py
mathlab_pg_api/spot_api.py
mathlab_pg_api_andrete-0.0.5.dist-info/LICENSE
mathlab_pg_api_andrete-0.0.5.dist-info/METADATA
mathlab_pg_api_andrete-0.0.5.dist-info/WHEEL
mathlab_pg_api_andrete-0.0.5.dist-info/top_level.txt
mathlab_pg_api_andrete-0.0.5.dist-info/RECORD
