Metadata-Version: 2.1
Name: mathlab-pg-api-andrete
Version: 0.0.5
Summary: mathlab pg api
Home-page: https://github.com/mathlabchina/Pythagoras
Author: andrete
Author-email: 13120309879@163.com
License: UNKNOWN
Platform: UNKNOWN
Classifier: Programming Language :: Python :: 3
Classifier: License :: OSI Approved :: MIT License
Classifier: Operating System :: OS Independent
